{"data":{"allDataJson":{"edges":[{"node":{"talksAndPublications":{"talks":[{"title":"Building a Karaoke Machine with Angular and HTML5 Speech Recognition","where":"ngconf 2018","url":"https://youtu.be/WHMyaTy7PME"},{"title":"Challenges of Upgrading to Angular - Interview with This Dot Media","where":"ngconf 2017","url":"https://youtu.be/xT4P2holvi0"},{"title":"Back from the past: A tale of helping others upgrade from Angular 1.x","where":"ngconf 2017","url":"https://youtu.be/FFhJSkI35U8"},{"title":"Staying Sane (dot) JS","where":"Nodevember 2016","url":"https://youtu.be/WP8oEhFXhZs"},{"title":"Upgrading from AngularJS to Angular","where":"Little Rock Tech Fest 2016","url":"https://youtu.be/FvTw_PDRWDQ"},{"title":"Is your team ready to learn React?","where":"Pluralsight Webinars","url":"https://youtu.be/vFbf-_FFuZ4"}]}}}]}},"pageContext":{}}